{
  "format_version": "1.8.0",
  "animations": {
    "leftdooropen": {
      "loop": "hold_on_last_frame",
      "animation_length": 0.72,
      "bones": {
        "left_door2": {
          "rotation": {
            "0.0": {
              "post": [
                0,
                0,
                0
              ],
              "lerp_mode": "catmullrom"
            },
            "0.32": {
              "post": [
                0,
                85,
                0
              ],
              "lerp_mode": "catmullrom"
            },
            "0.72": {
              "post": [
                0,
                80,
                0
              ],
              "lerp_mode": "catmullrom"
            }
          }
        }
      }
    },
    "leftdoorclose": {
      "loop": "hold_on_last_frame",
      "animation_length": 0.6,
      "bones": {
        "left_door2": {
          "rotation": {
            "0.0": {
              "post": [
                0,
                80,
                0
              ],
              "lerp_mode": "catmullrom"
            },
            "0.2": {
              "post": [
                0,
                6,
                0
              ],
              "lerp_mode": "catmullrom"
            },
            "0.4": {
              "post": [
                0,
                5,
                0
              ],
              "lerp_mode": "catmullrom"
            },
            "0.6": {
              "post": [
                0,
                0,
                0
              ],
              "lerp_mode": "catmullrom"
            }
          }
        }
      }
    },
    "rightdooropen": {
      "loop": "hold_on_last_frame",
      "animation_length": 0.72,
      "bones": {
        "right_door2": {
          "rotation": {
            "0.0": {
              "post": [
                0,
                0,
                0
              ],
              "lerp_mode": "catmullrom"
            },
            "0.32": {
              "post": [
                0,
                -85,
                0
              ],
              "lerp_mode": "catmullrom"
            },
            "0.72": {
              "post": [
                0,
                -80,
                0
              ],
              "lerp_mode": "catmullrom"
            }
          }
        }
      }
    },
    "rightdoorclose": {
      "loop": "hold_on_last_frame",
      "animation_length": 0.72,
      "bones": {
        "right_door2": {
          "rotation": {
            "0.0": {
              "post": [
                0,
                -80,
                0
              ],
              "lerp_mode": "catmullrom"
            },
            "0.2": {
              "post": [
                0,
                -6,
                0
              ],
              "lerp_mode": "catmullrom"
            },
            "0.4": {
              "post": [
                0,
                -5,
                0
              ],
              "lerp_mode": "catmullrom"
            },
            "0.6": {
              "post": [
                0,
                0,
                0
              ],
              "lerp_mode": "catmullrom"
            }
          }
        }
      }
    }
  }
}